kaiju/__init__.py
kaiju/__version__.py
kaiju/cKaiju.cpython-310-darwin.so
kaiju/robotGrid.py
kaiju/utils.py
kaiju/etc/fiducialCoords.csv
kaiju/etc/fps_DesignReference.txt
kaiju/etc/positionerTable.csv
kaiju/etc/robotGrid.html
kaiju/etc/robotGrid.js
kaiju/etc/wokCoords.csv
kaiju/include/coordio.h
kaiju/include/fiducial.h
kaiju/include/gfa.h
kaiju/include/robot.h
kaiju/include/robotGrid.h
kaiju/include/target.h
kaiju/include/utils.h
sdss_kaiju-1.4.1.dist-info/licenses/LICENSE.md
sdss_kaiju-1.4.1.dist-info/METADATA
sdss_kaiju-1.4.1.dist-info/WHEEL
sdss_kaiju-1.4.1.dist-info/top_level.txt
sdss_kaiju-1.4.1.dist-info/RECORD
