Metadata-Version: 2.4
Name: sdss-kaiju
Version: 1.4.1
Summary: Collision Avoidance for SDSS-V Positioners
Home-page: https://github.com/sdss/kaiju
Author: Conor Sayres
Author-email: csayres@uw.edu
License: BSD3
Keywords: astronomy software
Classifier: Intended Audience :: Science/Research
Classifier: License :: OSI Approved :: BSD License
Classifier: Natural Language :: English
Classifier: Operating System :: OS Independent
Classifier: Programming Language :: Python
License-File: LICENSE.md
Requires-Dist: matplotlib>=2.2.3
Requires-Dist: numpy<2,>=1.14.3
Requires-Dist: shapely<2.0.0,>=1.6.4.post1
Requires-Dist: descartes>=1.1.0
Requires-Dist: pybind11>=2.2.4
Requires-Dist: fitsio>=1.0.5
Requires-Dist: sdss-coordio>=1.2.1
Requires-Dist: psutil>=5.8.0
Requires-Dist: seaborn
Requires-Dist: simplification==0.7.10
Dynamic: author
Dynamic: author-email
Dynamic: classifier
Dynamic: description
Dynamic: home-page
Dynamic: keywords
Dynamic: license
Dynamic: license-file
Dynamic: requires-dist
Dynamic: summary
